kydns/__init__.py
kydns/kyd_exc.py
kydns/kyd_models.py
kydns/kyd_records.py
kydns/protocol.py
kydns-0.1.4.dist-info/LICENSE
kydns-0.1.4.dist-info/METADATA
kydns-0.1.4.dist-info/WHEEL
kydns-0.1.4.dist-info/RECORD
