Metadata-Version: 2.1
Name: kydns
Version: 0.1.4
Summary: A user-friendly DNS client and packet analyzer
License: MIT
Author: EliaOnceAgain
Author-email: eabunassar@gmail.com
Requires-Python: >=3.6,<4.0
Classifier: License :: OSI Approved :: MIT License
Classifier: Programming Language :: Python :: 3
Classifier: Programming Language :: Python :: 3.6
Classifier: Programming Language :: Python :: 3.7
Classifier: Programming Language :: Python :: 3.8
Classifier: Programming Language :: Python :: 3.9
Classifier: Programming Language :: Python :: 3.10
Classifier: Programming Language :: Python :: 3.11
